fnet_yaml/__init__.py
fnet_yaml/cli/__init__.py
fnet_yaml/cli/index.py
fnet_yaml/lib/__init__.py
fnet_yaml/lib/index.py
fnet_yaml-0.1.30.dist-info/METADATA
fnet_yaml-0.1.30.dist-info/WHEEL
fnet_yaml-0.1.30.dist-info/entry_points.txt
fnet_yaml-0.1.30.dist-info/top_level.txt
fnet_yaml-0.1.30.dist-info/RECORD
